<?xml version="1.0" encoding="windows-1252" ?>
<!DOCTYPE ViewObject SYSTEM "jbo_03_01.dtd">
<!---->
<ViewObject
  xmlns="http://xmlns.oracle.com/bc4j"
  Name="TblFgTrnMasterView"
  Version="12.2.1.11.57"
  InheritPersonalization="merge"
  BindingStyle="OracleName"
  CustomQuery="false"
  PageIterMode="Full"
  SelectList="TblFgTrnMaster.ID, 
       TblFgTrnMaster.VNO, 
       TblFgTrnMaster.VTP, 
       TblFgTrnMaster.DATED, 
       TblFgTrnMaster.PRO_FG_MASTER_ID, 
       TblFgTrnMaster.NARRATION, 
       TblFgTrnMaster.CREATED_DATE, 
       TblFgTrnMaster.CREATED_BY, 
       TblFgTrnMaster.UPDATED_DATE, 
       TblFgTrnMaster.UPDATED_BY, 
       TblFgTrnMaster.PROJECT_D_ID, 
       TblFgTrnMaster.PROJECT_D_D_ID, 
       TblFgTrnMaster.DEPARTMENT_ID, 
       TblFgTrnMaster.PROJECT_ID, 
       TblFgTrnMaster.PRO_FG_MASTER_ID AS PRO_FG_MASTER_ID1"
  FromList="TBL_FG_TRN_MASTER TblFgTrnMaster"
  Where="TblFgTrnMaster.PROJECT_ID = nvl(:getProId,TblFgTrnMaster.PROJECT_ID)">
  <Variable
    Name="getProId"
    Kind="where"
    Type="java.math.BigDecimal">
    <TransientExpression
      Name="VariableScript"
      CodeSourceName="TblFgTrnMasterView"/>
  </Variable>
  <ViewAccessor
    Name="Voucher_Type1"
    ViewObjectName="model.LOV.Voucher_Type"
    RowLevelBinds="true"/>
  <ViewAccessor
    Name="Pro_FG_Master_LOV1"
    ViewObjectName="model.LOV.Pro_FG_Master_LOV"
    RowLevelBinds="true"/>
  <ViewAccessor
    Name="Department_Name_LOV1"
    ViewObjectName="model.LOV.Department_Name_LOV"
    RowLevelBinds="true"/>
  <ViewAccessor
    Name="Project_Name_LOV1"
    ViewObjectName="model.LOV.Project_Name_LOV"
    RowLevelBinds="true"/>
  <ViewAccessor
    Name="Project_Centers_Dep_LOV1"
    ViewObjectName="model.LOV.Project_Centers_Dep_LOV"
    RowLevelBinds="true">
    <ParameterMap>
      <PIMap Variable="Projtid">
        <TransientExpression
          trustMode="untrusted"
          Name="ExpressionScript"><![CDATA[ProjectId]]></TransientExpression>
      </PIMap>
    </ParameterMap>
  </ViewAccessor>
  <ViewAccessor
    Name="Pro_FG_Master_NotIN_LOV1"
    ViewObjectName="model.LOV.Pro_FG_Master_NotIN_LOV"
    RowLevelBinds="true">
    <ParameterMap>
      <PIMap Variable="get_ProID">
        <TransientExpression
          trustMode="untrusted"
          Name="ExpressionScript"><![CDATA[ProjectId]]></TransientExpression>
      </PIMap>
    </ParameterMap>
  </ViewAccessor>
  <ListBinding
    Name="LOV_Vtp"
    ListVOName="Voucher_Type1"
    ListRangeSize="-1"
    NullValueFlag="none"
    MRUCount="0">
    <AttrArray Name="AttrNames">
      <Item Value="Vtp"/>
    </AttrArray>
    <AttrArray Name="AttrExpressions"/>
    <AttrArray Name="ListAttrNames">
      <Item Value="DBAttr"/>
    </AttrArray>
    <AttrArray Name="ListDisplayAttrNames">
      <Item Value="ViewAttr"/>
    </AttrArray>
    <DisplayCriteria/>
  </ListBinding>
  <ListBinding
    Name="LOV_DepartmentId"
    ListVOName="Department_Name_LOV1"
    ListRangeSize="-1"
    NullValueFlag="none"
    MRUCount="0">
    <AttrArray Name="AttrNames">
      <Item Value="DepartmentId"/>
    </AttrArray>
    <AttrArray Name="AttrExpressions"/>
    <AttrArray Name="ListAttrNames">
      <Item Value="Id"/>
    </AttrArray>
    <AttrArray Name="ListDisplayAttrNames">
      <Item Value="Name"/>
    </AttrArray>
    <DisplayCriteria/>
  </ListBinding>
  <ListBinding
    Name="LOV_ProjectId"
    ListVOName="Project_Name_LOV1"
    ListRangeSize="-1"
    NullValueFlag="none"
    MRUCount="0">
    <AttrArray Name="AttrNames">
      <Item Value="ProjectId"/>
    </AttrArray>
    <AttrArray Name="AttrExpressions"/>
    <AttrArray Name="ListAttrNames">
      <Item Value="Id"/>
    </AttrArray>
    <AttrArray Name="ListDisplayAttrNames">
      <Item Value="Name"/>
    </AttrArray>
    <DisplayCriteria/>
  </ListBinding>
  <ListBinding
    Name="LOV_ProjectDId"
    ListVOName="Project_Centers_Dep_LOV1"
    ListRangeSize="-1"
    NullValueFlag="none"
    MRUCount="0">
    <AttrArray Name="AttrNames">
      <Item Value="ProjectDId"/>
    </AttrArray>
    <AttrArray Name="AttrExpressions"/>
    <AttrArray Name="ListAttrNames">
      <Item Value="Id"/>
    </AttrArray>
    <AttrArray Name="ListDisplayAttrNames">
      <Item Value="Name"/>
    </AttrArray>
    <DisplayCriteria/>
  </ListBinding>
  <ListBinding
    Name="LOV_ProFgMasterIdStatic"
    ListVOName="Pro_FG_Master_LOV1"
    ListRangeSize="-1"
    NullValueFlag="none"
    MRUCount="0">
    <AttrArray Name="AttrNames">
      <Item Value="ProFgMasterIdStatic"/>
    </AttrArray>
    <AttrArray Name="AttrExpressions"/>
    <AttrArray Name="ListAttrNames">
      <Item Value="Id"/>
    </AttrArray>
    <AttrArray Name="ListDisplayAttrNames">
      <Item Value="Vno"/>
      <Item Value="Vtp"/>
    </AttrArray>
    <DisplayCriteria/>
  </ListBinding>
  <ListBinding
    Name="LOV_ProFgMasterId"
    ListVOName="Pro_FG_Master_NotIN_LOV1"
    ListRangeSize="-1"
    NullValueFlag="none"
    MRUCount="0">
    <AttrArray Name="AttrNames">
      <Item Value="ProFgMasterId"/>
    </AttrArray>
    <AttrArray Name="AttrExpressions"/>
    <AttrArray Name="DerivedAttrNames">
      <Item Value="DepartmentId"/>
      <Item Value="ProjectId"/>
      <Item Value="ProjectDId"/>
    </AttrArray>
    <AttrArray Name="ListAttrNames">
      <Item Value="Id"/>
      <Item Value="DepartmentId"/>
      <Item Value="ProjectId"/>
      <Item Value="ProjectDId"/>
    </AttrArray>
    <AttrArray Name="ListDisplayAttrNames">
      <Item Value="Vno"/>
      <Item Value="Dated"/>
      <Item Value="Vtp"/>
      <Item Value="Id"/>
    </AttrArray>
    <DisplayCriteria/>
  </ListBinding>
  <EntityUsage
    Name="TblFgTrnMaster"
    Entity="model.ERP.EO.TblFgTrnMaster"/>
  <ViewAttribute
    Name="Id"
    IsNotNull="true"
    PrecisionRule="true"
    EntityAttrName="Id"
    EntityUsage="TblFgTrnMaster"
    AliasName="ID"/>
  <ViewAttribute
    Name="Vno"
    PrecisionRule="true"
    EntityAttrName="Vno"
    EntityUsage="TblFgTrnMaster"
    AliasName="VNO"/>
  <ViewAttribute
    Name="Vtp"
    PrecisionRule="true"
    EntityAttrName="Vtp"
    EntityUsage="TblFgTrnMaster"
    AliasName="VTP"
    LOVName="LOV_Vtp">
    <Properties>
      <SchemaBasedProperties>
        <CONTROLTYPE
          Value="combo"/>
      </SchemaBasedProperties>
    </Properties>
  </ViewAttribute>
  <ViewAttribute
    Name="Dated"
    PrecisionRule="true"
    EntityAttrName="Dated"
    EntityUsage="TblFgTrnMaster"
    AliasName="DATED">
    <Properties>
      <SchemaBasedProperties>
        <FMT_FORMAT
          ResId="model.ERP.VO.TblFgTrnMasterView.Dated_FMT_FORMAT"/>
        <FMT_FORMATTER
          ResId="model.ERP.VO.TblFgTrnMasterView.Dated_FMT_FORMATTER"/>
      </SchemaBasedProperties>
    </Properties>
  </ViewAttribute>
  <ViewAttribute
    Name="ProFgMasterId"
    PrecisionRule="true"
    EntityAttrName="ProFgMasterId"
    EntityUsage="TblFgTrnMaster"
    AliasName="PRO_FG_MASTER_ID"
    LOVName="LOV_ProFgMasterId">
    <Properties>
      <SchemaBasedProperties>
        <CONTROLTYPE
          Value="combo"/>
      </SchemaBasedProperties>
    </Properties>
  </ViewAttribute>
  <ViewAttribute
    Name="Narration"
    PrecisionRule="true"
    EntityAttrName="Narration"
    EntityUsage="TblFgTrnMaster"
    AliasName="NARRATION"/>
  <ViewAttribute
    Name="CreatedDate"
    PrecisionRule="true"
    EntityAttrName="CreatedDate"
    EntityUsage="TblFgTrnMaster"
    AliasName="CREATED_DATE"
    IsUpdateable="false"/>
  <ViewAttribute
    Name="CreatedBy"
    PrecisionRule="true"
    EntityAttrName="CreatedBy"
    EntityUsage="TblFgTrnMaster"
    AliasName="CREATED_BY"/>
  <ViewAttribute
    Name="UpdatedDate"
    PrecisionRule="true"
    EntityAttrName="UpdatedDate"
    EntityUsage="TblFgTrnMaster"
    AliasName="UPDATED_DATE"
    IsUpdateable="false"/>
  <ViewAttribute
    Name="UpdatedBy"
    PrecisionRule="true"
    EntityAttrName="UpdatedBy"
    EntityUsage="TblFgTrnMaster"
    AliasName="UPDATED_BY"/>
  <ViewAttribute
    Name="ProjectDId"
    PrecisionRule="true"
    EntityAttrName="ProjectDId"
    EntityUsage="TblFgTrnMaster"
    AliasName="PROJECT_D_ID"
    LOVName="LOV_ProjectDId">
    <Properties>
      <SchemaBasedProperties>
        <CONTROLTYPE
          Value="combo"/>
      </SchemaBasedProperties>
    </Properties>
  </ViewAttribute>
  <ViewAttribute
    Name="ProjectDDId"
    PrecisionRule="true"
    EntityAttrName="ProjectDDId"
    EntityUsage="TblFgTrnMaster"
    AliasName="PROJECT_D_D_ID"/>
  <ViewAttribute
    Name="DepartmentId"
    PrecisionRule="true"
    EntityAttrName="DepartmentId"
    EntityUsage="TblFgTrnMaster"
    AliasName="DEPARTMENT_ID"
    LOVName="LOV_DepartmentId">
    <Properties>
      <SchemaBasedProperties>
        <CONTROLTYPE
          Value="combo"/>
      </SchemaBasedProperties>
    </Properties>
  </ViewAttribute>
  <ViewAttribute
    Name="ProjectId"
    PrecisionRule="true"
    EntityAttrName="ProjectId"
    EntityUsage="TblFgTrnMaster"
    AliasName="PROJECT_ID"
    LOVName="LOV_ProjectId">
    <Properties>
      <SchemaBasedProperties>
        <CONTROLTYPE
          Value="combo"/>
      </SchemaBasedProperties>
    </Properties>
  </ViewAttribute>
  <ViewAttribute
    Name="ProFgMasterIdStatic"
    PrecisionRule="true"
    EntityAttrName="ProFgMasterId"
    EntityUsage="TblFgTrnMaster"
    AliasName="PRO_FG_MASTER_ID1"
    LOVName="LOV_ProFgMasterIdStatic">
    <Properties>
      <SchemaBasedProperties>
        <CONTROLTYPE
          Value="combo"/>
      </SchemaBasedProperties>
    </Properties>
  </ViewAttribute>
  <ViewLinkAccessor
    Name="TblFgTrnDetailView"
    ViewLink="model.ERP.VO.FkFgTrnDetailMasterLink"
    Type="oracle.jbo.RowIterator"
    IsUpdateable="false"/>
  <ResourceBundle>
    <PropertiesBundle
      PropertiesFile="model.ModelBundle"/>
  </ResourceBundle>
</ViewObject>
